rpst/__init__.py
rpst/api.py
rpst/base.py
rpst/coreutils.py
rpst/scraper.py
reddit_post_scraping_tool-2.0.0.0.dist-info/LICENSE
reddit_post_scraping_tool-2.0.0.0.dist-info/METADATA
reddit_post_scraping_tool-2.0.0.0.dist-info/WHEEL
reddit_post_scraping_tool-2.0.0.0.dist-info/entry_points.txt
reddit_post_scraping_tool-2.0.0.0.dist-info/top_level.txt
reddit_post_scraping_tool-2.0.0.0.dist-info/RECORD
