Metadata-Version: 2.1
Name: reddit-post-scraping-tool
Version: 2.0.0.0
Summary: Retrieve Reddit posts that contain the specified keyword from a specified subreddit.
Author-email: Richard Mwewa <rly0nheart@duck.com>
License: MIT License
Project-URL: homepage, https://github.com/bellingcat
Project-URL: documentation, https://github.com/bellingcat/reddit-post-scraping-tool/wiki
Project-URL: repository, https://github.com/bellingcat/reddit-post-scraping-tool.git
Keywords: reddit-crawler,reddit-scraping,reddit,reddit-api
Classifier: Development Status :: 5 - Production/Stable
Classifier: Programming Language :: Python :: 3
Classifier: Programming Language :: Visual Basic
Classifier: Intended Audience :: End Users/Desktop
Classifier: License :: OSI Approved :: MIT License
Classifier: Operating System :: OS Independent
Classifier: Natural Language :: English
Requires-Python: >=3.8
License-File: LICENSE
Requires-Dist: rich
Requires-Dist: aiohttp
Requires-Dist: rich-argparse
